mansaa/__init__.py
mansaapy-0.1.6.dist-info/METADATA
mansaapy-0.1.6.dist-info/RECORD
mansaapy-0.1.6.dist-info/WHEEL
mansaapy-0.1.6.dist-info/top_level.txt
